{
  "activity": [
    {
      "type": "commit",
      "id": "21cd87b7",
      "author": "Milo",
      "timestamp": "2026-02-14 18:39:06 -0500",
      "message": "chore: auto-sync dashboard data"
    },
    {
      "type": "commit",
      "id": "c30262e8",
      "author": "Milo",
      "timestamp": "2026-02-14 18:37:11 -0500",
      "message": "feat: add In Plain English section to Agent Ideas cards"
    },
    {
      "type": "commit",
      "id": "aff2b736",
      "author": "Milo",
      "timestamp": "2026-02-14 18:34:07 -0500",
      "message": "chore: auto-sync dashboard data"
    },
    {
      "type": "commit",
      "id": "b1719823",
      "author": "Milo",
      "timestamp": "2026-02-14 18:29:07 -0500",
      "message": "fix: TypeScript index type error in budget map"
    },
    {
      "type": "commit",
      "id": "37e1589e",
      "author": "Milo",
      "timestamp": "2026-02-14 18:29:05 -0500",
      "message": "chore: auto-sync dashboard data"
    },
    {
      "type": "commit",
      "id": "c2b51d33",
      "author": "Milo",
      "timestamp": "2026-02-14 18:28:25 -0500",
      "message": "feat: add budget tier selector to Agent Assist (open-source to /mo)"
    },
    {
      "type": "commit",
      "id": "725d93ad",
      "author": "Milo",
      "timestamp": "2026-02-14 18:24:05 -0500",
      "message": "chore: auto-sync dashboard data"
    },
    {
      "type": "commit",
      "id": "d4723b50",
      "author": "Milo",
      "timestamp": "2026-02-14 18:19:26 -0500",
      "message": "feat: add 'In Plain English' explainer to every Agent Assist resource card"
    },
    {
      "type": "commit",
      "id": "b9dd7a94",
      "author": "Milo",
      "timestamp": "2026-02-14 18:19:06 -0500",
      "message": "chore: auto-sync dashboard data"
    },
    {
      "type": "commit",
      "id": "d0c1da6f",
      "author": "Milo",
      "timestamp": "2026-02-14 18:11:04 -0500",
      "message": "refactor: switch Agent Assist persistence from localStorage to Supabase"
    },
    {
      "type": "commit",
      "id": "ae52e483",
      "author": "Milo",
      "timestamp": "2026-02-14 18:09:20 -0500",
      "message": "feat: persist deletes/verifies to localStorage, add 'Have it' button that removes resource"
    },
    {
      "type": "commit",
      "id": "dbe38516",
      "author": "Milo",
      "timestamp": "2026-02-14 18:09:06 -0500",
      "message": "chore: auto-sync dashboard data"
    },
    {
      "type": "commit",
      "id": "e2a220e0",
      "author": "Milo",
      "timestamp": "2026-02-14 17:59:04 -0500",
      "message": "chore: auto-sync dashboard data"
    },
    {
      "type": "commit",
      "id": "dfbccc83",
      "author": "Milo",
      "timestamp": "2026-02-14 17:54:09 -0500",
      "message": "chore: auto-sync dashboard data"
    },
    {
      "type": "commit",
      "id": "34f13d44",
      "author": "Milo",
      "timestamp": "2026-02-14 17:49:04 -0500",
      "message": "chore: auto-sync dashboard data"
    },
    {
      "type": "commit",
      "id": "8103daa6",
      "author": "Milo",
      "timestamp": "2026-02-14 17:44:04 -0500",
      "message": "chore: auto-sync dashboard data"
    },
    {
      "type": "commit",
      "id": "4ebbf3c6",
      "author": "Milo",
      "timestamp": "2026-02-14 17:39:04 -0500",
      "message": "chore: auto-sync dashboard data"
    },
    {
      "type": "commit",
      "id": "9ee7fac6",
      "author": "Milo",
      "timestamp": "2026-02-14 17:34:04 -0500",
      "message": "chore: auto-sync dashboard data"
    },
    {
      "type": "commit",
      "id": "fe19311b",
      "author": "Milo",
      "timestamp": "2026-02-14 17:29:04 -0500",
      "message": "chore: auto-sync dashboard data"
    },
    {
      "type": "commit",
      "id": "df9925b3",
      "author": "Milo",
      "timestamp": "2026-02-14 17:24:04 -0500",
      "message": "chore: auto-sync dashboard data"
    },
    {
      "type": "commit",
      "id": "67af68b7",
      "author": "Milo",
      "timestamp": "2026-02-14 17:19:04 -0500",
      "message": "chore: auto-sync dashboard data"
    },
    {
      "type": "commit",
      "id": "8d08341a",
      "author": "Milo",
      "timestamp": "2026-02-14 17:14:08 -0500",
      "message": "chore: auto-sync dashboard data"
    },
    {
      "type": "commit",
      "id": "d070d489",
      "author": "Milo",
      "timestamp": "2026-02-14 17:09:06 -0500",
      "message": "chore: auto-sync dashboard data"
    },
    {
      "type": "commit",
      "id": "03023430",
      "author": "Milo",
      "timestamp": "2026-02-14 17:04:04 -0500",
      "message": "chore: auto-sync dashboard data"
    },
    {
      "type": "commit",
      "id": "afdf6891",
      "author": "Milo",
      "timestamp": "2026-02-14 16:59:04 -0500",
      "message": "chore: auto-sync dashboard data"
    },
    {
      "type": "commit",
      "id": "ace6527d",
      "author": "Milo",
      "timestamp": "2026-02-14 16:54:04 -0500",
      "message": "chore: auto-sync dashboard data"
    },
    {
      "type": "commit",
      "id": "c645c60f",
      "author": "Milo",
      "timestamp": "2026-02-14 16:49:04 -0500",
      "message": "chore: auto-sync dashboard data"
    },
    {
      "type": "commit",
      "id": "da4c3697",
      "author": "Milo",
      "timestamp": "2026-02-14 16:44:04 -0500",
      "message": "chore: auto-sync dashboard data"
    },
    {
      "type": "commit",
      "id": "70cbf6a8",
      "author": "Milo",
      "timestamp": "2026-02-14 16:39:05 -0500",
      "message": "chore: auto-sync dashboard data"
    },
    {
      "type": "commit",
      "id": "c22946b8",
      "author": "Milo",
      "timestamp": "2026-02-14 16:34:04 -0500",
      "message": "chore: auto-sync dashboard data"
    },
    {
      "type": "commit",
      "id": "0af48108",
      "author": "Milo",
      "timestamp": "2026-02-14 16:29:04 -0500",
      "message": "chore: auto-sync dashboard data"
    },
    {
      "type": "commit",
      "id": "308319cd",
      "author": "Milo",
      "timestamp": "2026-02-14 16:24:04 -0500",
      "message": "chore: auto-sync dashboard data"
    },
    {
      "type": "commit",
      "id": "a1b89334",
      "author": "Milo",
      "timestamp": "2026-02-14 16:19:29 -0500",
      "message": "feat: Agent Assist - add delete button + web-search-powered generation (no repeats)"
    },
    {
      "type": "commit",
      "id": "67cdaa3f",
      "author": "Milo",
      "timestamp": "2026-02-14 16:19:06 -0500",
      "message": "chore: auto-sync dashboard data"
    },
    {
      "type": "commit",
      "id": "cb7b760d",
      "author": "Milo",
      "timestamp": "2026-02-14 16:14:09 -0500",
      "message": "chore: auto-sync dashboard data"
    },
    {
      "type": "commit",
      "id": "7f5a2be9",
      "author": "Milo",
      "timestamp": "2026-02-14 16:11:11 -0500",
      "message": "Transform agent idea templates to storytelling format with multiple name suggestions and simplified language throughout"
    },
    {
      "type": "commit",
      "id": "770a8061",
      "author": "Milo",
      "timestamp": "2026-02-14 16:09:06 -0500",
      "message": "chore: auto-sync dashboard data"
    },
    {
      "type": "commit",
      "id": "265791fc",
      "author": "Milo",
      "timestamp": "2026-02-14 16:04:10 -0500",
      "message": "chore: auto-sync dashboard data"
    },
    {
      "type": "commit",
      "id": "1f41cad9",
      "author": "Milo",
      "timestamp": "2026-02-14 16:02:25 -0500",
      "message": "Move Agent Reasoning to full-width section for better readability"
    },
    {
      "type": "commit",
      "id": "17dfb146",
      "author": "Milo",
      "timestamp": "2026-02-14 15:59:05 -0500",
      "message": "chore: auto-sync dashboard data"
    },
    {
      "type": "commit",
      "id": "e3dc70d0",
      "author": "Milo",
      "timestamp": "2026-02-14 15:54:04 -0500",
      "message": "chore: auto-sync dashboard data"
    },
    {
      "type": "commit",
      "id": "40753859",
      "author": "Milo",
      "timestamp": "2026-02-14 15:49:04 -0500",
      "message": "chore: auto-sync dashboard data"
    },
    {
      "type": "commit",
      "id": "21c01f05",
      "author": "Milo",
      "timestamp": "2026-02-14 15:44:04 -0500",
      "message": "chore: auto-sync dashboard data"
    },
    {
      "type": "commit",
      "id": "08aab7a5",
      "author": "Milo",
      "timestamp": "2026-02-14 15:39:05 -0500",
      "message": "chore: auto-sync dashboard data"
    },
    {
      "type": "commit",
      "id": "7deea4a1",
      "author": "Milo",
      "timestamp": "2026-02-14 15:37:00 -0500",
      "message": "Enhance agent ideas interface with 'explain like I'm 5' approach - Add prominent 'What is this idea?' section, move Agent Reasoning to blue box next to Development Time, simplify all language for accessibility"
    },
    {
      "type": "commit",
      "id": "a548919c",
      "author": "Milo",
      "timestamp": "2026-02-14 15:34:06 -0500",
      "message": "chore: auto-sync dashboard data"
    },
    {
      "type": "commit",
      "id": "1f251d80",
      "author": "Milo",
      "timestamp": "2026-02-14 15:29:10 -0500",
      "message": "chore: auto-sync dashboard data"
    },
    {
      "type": "commit",
      "id": "4713b073",
      "author": "Milo",
      "timestamp": "2026-02-14 15:24:07 -0500",
      "message": "chore: auto-sync dashboard data"
    },
    {
      "type": "commit",
      "id": "baeb8366",
      "author": "Milo",
      "timestamp": "2026-02-14 15:22:00 -0500",
      "message": "feat: rewrite DNA Scanner with brand tokens - dark+amber matching /os theme"
    },
    {
      "type": "commit",
      "id": "f2c12aff",
      "author": "Milo",
      "timestamp": "2026-02-14 15:19:07 -0500",
      "message": "chore: auto-sync dashboard data"
    },
    {
      "type": "cron_run",
      "id": "bc892137",
      "timestamp": "2026-02-14T14:10:43.818Z",
      "message": "Cron run: ok",
      "jobId": "bc892137-9697-492b-920d-4bbeca1cea9c"
    },
    {
      "type": "cron_run",
      "id": "923bc5c8",
      "timestamp": "2026-02-14T14:10:28.502Z",
      "message": "Cron run: ok",
      "jobId": "923bc5c8-e0d0-4047-9394-60176223436e"
    },
    {
      "type": "cron_run",
      "id": "7face9bc",
      "timestamp": "2026-02-14T14:09:28.298Z",
      "message": "Cron run: ok",
      "jobId": "7face9bc-30f0-4b2a-85ca-8c57f5351cdb"
    },
    {
      "type": "cron_run",
      "id": "44fbe02a",
      "timestamp": "2026-02-14T14:03:18.577Z",
      "message": "Cron run: ok",
      "jobId": "44fbe02a-c8f8-4921-9a55-2d97efd34b9c"
    },
    {
      "type": "cron_run",
      "id": "d737c8a2",
      "timestamp": "2026-02-14T13:37:43.964Z",
      "message": "Cron run: ok",
      "jobId": "d737c8a2-21bb-4486-aa24-15d95152d8a9"
    },
    {
      "type": "cron_run",
      "id": "de37c19d",
      "timestamp": "2026-02-14T13:10:48.098Z",
      "message": "Cron run: ok",
      "jobId": "de37c19d-2152-46cf-81ae-f46cd63cbd79"
    },
    {
      "type": "cron_run",
      "id": "4822e39c",
      "timestamp": "2026-02-14T13:03:36.656Z",
      "message": "Cron run: ok",
      "jobId": "4822e39c-38a2-4529-894c-5163ea4232b4"
    },
    {
      "type": "cron_run",
      "id": "60a36293",
      "timestamp": "2026-02-14T12:46:42.290Z",
      "message": "Cron run: ok",
      "jobId": "60a36293-bf9a-431d-b2d9-f2b53b3792f5"
    },
    {
      "type": "cron_run",
      "id": "bee7eb71",
      "timestamp": "2026-02-14T12:30:12.060Z",
      "message": "Cron run: ok",
      "jobId": "bee7eb71-dbd4-49c7-a1a9-1bb94844b589"
    },
    {
      "type": "cron_run",
      "id": "7335853f",
      "timestamp": "2026-02-14T12:15:12.525Z",
      "message": "Cron run: ok",
      "jobId": "7335853f-b007-4576-b7d2-2146128315f0"
    },
    {
      "type": "cron_run",
      "id": "e3746cbd",
      "timestamp": "2026-02-14T12:06:46.784Z",
      "message": "Cron run: ok",
      "jobId": "e3746cbd-d836-4104-aa7d-8f20f69b385e"
    },
    {
      "type": "cron_run",
      "id": "61b6eecf",
      "timestamp": "2026-02-14T08:10:02.481Z",
      "message": "Cron run: ok",
      "jobId": "61b6eecf-139d-472b-b7f0-f5e1ad9cc0dd"
    },
    {
      "type": "cron_run",
      "id": "866b45c4",
      "timestamp": "2026-02-14T01:02:01.352Z",
      "message": "Cron run: ok",
      "jobId": "866b45c4-d91c-4178-87df-d55a825b84a2"
    }
  ],
  "generatedAt": "2026-02-14T23:44:04.709Z"
}